MANIFEST.in
README.md
bridge.sh
wenux.py
Gui/Gui.py
Gui/Logging.py
Gui/Qt5.py
Tc/Filter.py
Tc/Netem.py
Tc/Tbf.py
Tc/TcCollection.py
Tc/TcWrapper.py
Tc/__init__.py
Utils/ArgParser.py
Utils/ResourceMonitor.py
Utils/Subprocess.py
Utils/__init__.py
wenux.egg-info/PKG-INFO
wenux.egg-info/SOURCES.txt
wenux.egg-info/dependency_links.txt
wenux.egg-info/top_level.txt
wenux-1.0.3.dist-info/LICENSE
wenux-1.0.3.dist-info/METADATA
wenux-1.0.3.dist-info/WHEEL
wenux-1.0.3.dist-info/top_level.txt
wenux-1.0.3.dist-info/RECORD
