Metadata-Version: 2.1
Name: wenux
Version: 1.0.3
Summary: WAN emulator for Linux
Home-page: https://github.com/Axonis/DP
Author: Jozef Urbanovský
Author-email: jurbanov@redhat.com
License: UNKNOWN
Platform: UNKNOWN
Classifier: Programming Language :: Python :: 3.7
Classifier: License :: OSI Approved :: GNU General Public License v3 (GPLv3)
Classifier: Operating System :: POSIX :: Linux
Requires-Python: >=3.7
